{
  "main": {
    "id": "0d6be3de1e46fd24",
    "type": "split",
    "children": [
      {
        "id": "d871a1d5a67db20e",
        "type": "tabs",
        "children": [
          {
            "id": "675528cacb1c9a09",
            "type": "leaf",
            "state": {
              "type": "markdown",
              "state": {
                "file": "00-索引/资料索引.md",
                "mode": "source",
                "source": false
              },
              "icon": "lucide-file",
              "title": "资料索引"
            }
          }
        ]
      }
    ],
    "direction": "vertical"
  },
  "left": {
    "id": "04c1413edae1a998",
    "type": "split",
    "children": [
      {
        "id": "0b921a16e3993688",
        "type": "tabs",
        "children": [
          {
            "id": "74860aa526967a70",
            "type": "leaf",
            "state": {
              "type": "file-explorer",
              "state": {
                "sortOrder": "alphabetical",
                "autoReveal": false
              },
              "icon": "lucide-folder-closed",
              "title": "文件列表"
            }
          },
          {
            "id": "2ccccf7f717911f5",
            "type": "leaf",
            "state": {
              "type": "search",
              "state": {
                "query": "",
                "matchingCase": false,
                "explainSearch": false,
                "collapseAll": false,
                "extraContext": false,
                "sortOrder": "alphabetical"
              },
              "icon": "lucide-search",
              "title": "搜索"
            }
          },
          {
            "id": "7952aad0719fbad4",
            "type": "leaf",
            "state": {
              "type": "bookmarks",
              "state": {},
              "icon": "lucide-bookmark",
              "title": "书签"
            }
          }
        ]
      }
    ],
    "direction": "horizontal",
    "width": 692.5
  },
  "right": {
    "id": "6267a3ea32e720b5",
    "type": "split",
    "children": [
      {
        "id": "50d9c8ed6400aa69",
        "type": "tabs",
        "children": [
          {
            "id": "23d257f63dbb9cad",
            "type": "leaf",
            "state": {
              "type": "backlink",
              "state": {
                "file": "02-知识点库/公共基础知识/最新泗洪县事业单位《公共基础知识》/九、核心精心整理资料——金牌讲义/九、核心独家资料——金牌讲义/公共基础知识讲义——法律篇.pdf",
                "collapseAll": false,
                "extraContext": false,
                "sortOrder": "alphabetical",
                "showSearch": false,
                "searchQuery": "",
                "backlinkCollapsed": false,
                "unlinkedCollapsed": true
              },
              "icon": "links-coming-in",
              "title": "公共基础知识讲义——法律篇 的反向链接列表"
            }
          },
          {
            "id": "3c59f544ab2e331b",
            "type": "leaf",
            "state": {
              "type": "outgoing-link",
              "state": {
                "file": "02-知识点库/公共基础知识/最新泗洪县事业单位《公共基础知识》/九、核心精心整理资料——金牌讲义/九、核心独家资料——金牌讲义/公共基础知识讲义——法律篇.pdf",
                "linksCollapsed": false,
                "unlinkedCollapsed": true
              },
              "icon": "links-going-out",
              "title": "公共基础知识讲义——法律篇 的出链列表"
            }
          },
          {
            "id": "1b7f68520f7e1e93",
            "type": "leaf",
            "state": {
              "type": "tag",
              "state": {
                "sortOrder": "frequency",
                "useHierarchy": true,
                "showSearch": false,
                "searchQuery": ""
              },
              "icon": "lucide-tags",
              "title": "标签"
            }
          },
          {
            "id": "d7e80a8775944b34",
            "type": "leaf",
            "state": {
              "type": "outline",
              "state": {
                "file": "02-知识点库/公共基础知识/最新泗洪县事业单位《公共基础知识》/九、核心精心整理资料——金牌讲义/九、核心独家资料——金牌讲义/公共基础知识讲义——法律篇.pdf",
                "followCursor": false,
                "showSearch": false,
                "searchQuery": ""
              },
              "icon": "lucide-list",
              "title": "公共基础知识讲义——法律篇 的大纲"
            }
          }
        ]
      }
    ],
    "direction": "horizontal",
    "width": 300,
    "collapsed": true
  },
  "left-ribbon": {
    "hiddenItems": {
      "switcher:打开快速切换": false,
      "graph:查看关系图谱": false,
      "canvas:新建白板": false,
      "daily-notes:打开/创建今天的日记": false,
      "templates:插入模板": false,
      "command-palette:打开命令面板": false,
      "bases:创建新数据库": false
    }
  },
  "active": "675528cacb1c9a09",
  "lastOpenFiles": [
    "02-知识点库/公共基础知识/最新泗洪县事业单位《公共基础知识》/九、核心精心整理资料——金牌讲义/九、核心独家资料——金牌讲义/公共基础知识讲义——法律篇.pdf",
    "02-知识点库/公共基础知识/最新泗洪县事业单位《公共基础知识》/九、核心精心整理资料——金牌讲义/九、核心独家资料——金牌讲义/公共基础知识讲义——经济篇.md",
    "02-知识点库/公共基础知识/最新泗洪县事业单位《公共基础知识》/九、核心精心整理资料——金牌讲义/九、核心独家资料——金牌讲义/公共基础知识讲义——法律篇.md",
    "02-知识点库/公共基础知识/最新泗洪县事业单位《公共基础知识》/九、核心精心整理资料——金牌讲义/九、核心独家资料——金牌讲义/公共基础知识讲义——管理篇.md",
    "02-知识点库/公共基础知识/最新泗洪县事业单位《公共基础知识》/九、核心精心整理资料——金牌讲义/九、核心独家资料——金牌讲义/公共基础知识讲义——科技篇.md",
    "02-知识点库/公共基础知识/最新泗洪县事业单位《公共基础知识》/九、核心精心整理资料——金牌讲义/九、核心独家资料——金牌讲义/公共基础知识讲义——政治篇.md",
    "02-知识点库/公共基础知识/最新泗洪县事业单位《公共基础知识》/九、核心精心整理资料——金牌讲义/九、核心独家资料——金牌讲义/公共基础知识讲义——历史文化篇.md",
    "02-知识点库/公共基础知识/最新泗洪县事业单位《公共基础知识》/九、核心精心整理资料——金牌讲义/九、核心独家资料——金牌讲义/公共基础知识讲义——国情地理篇.md",
    "02-知识点库/公共基础知识/最新泗洪县事业单位《公共基础知识》/九、核心精心整理资料——金牌讲义/九、核心独家资料——金牌讲义/公共基础知识讲义.md",
    "02-知识点库/公共基础知识/最新泗洪县事业单位《公共基础知识》/九、核心精心整理资料——金牌讲义/九、核心独家资料——金牌讲义/公共基础知识讲义——公文篇.md",
    "02-知识点库/公共基础知识/最新泗洪县事业单位《公共基础知识》/九、核心精心整理资料——金牌讲义/九、核心独家资料——金牌讲义/公共基础知识讲义——职业道德篇.md",
    "02-知识点库/公共基础知识/泗洪县事业单位【全新冲刺版】【公共基础知识】考点+预测押题库+重点必考+速学讲义/全新公共基础知识预测押题题库/全新公共基础知识预测押题题库.md",
    "02-知识点库/公共基础知识/泗洪县事业单位【全新冲刺版】【公共基础知识】考点+预测押题库+重点必考+速学讲义/全新公共基础知识预测押题题库/全新公共基础知识预测押题题库【答案解析】.md",
    "02-知识点库/公共基础知识/泗洪县事业单位【全新冲刺版】【公共基础知识】考点+预测押题库+重点必考+速学讲义/更新版【公共基础知识】高分笔记整合版知识点全覆盖.md",
    "02-知识点库/公共基础知识/泗洪县事业单位【全新冲刺版】【公共基础知识】考点+预测押题库+重点必考+速学讲义/全新必过公共基础知识彩色笔记（答案）.md",
    "02-知识点库/公共基础知识/泗洪县事业单位【完整版】《公共基础知识》新版必过复习资料/新版《公共基础知识》高分重点讲义/5.赠送部分资料(仅供参考)/02公共基础知识极致模考答案解析.md",
    "02-知识点库/公共基础知识/泗洪县事业单位【完整版】《公共基础知识》新版必过复习资料/新版《公共基础知识》高分重点讲义/5.赠送部分资料(仅供参考)/01公共基础知识极致模考题本8套.md",
    "02-知识点库/公共基础知识/泗洪县事业单位【完整版】《公共基础知识》新版必过复习资料/新版《公共基础知识》高分重点讲义/5.赠送部分资料(仅供参考)/03公共基础知识真题4套+解析.md",
    "02-知识点库/公共基础知识/泗洪县事业单位【完整版】《公共基础知识》新版必过复习资料/新版《公共基础知识》高分重点讲义/2.公共基础知识—专项特训/基础强化-法理学.md",
    "02-知识点库/公共基础知识/泗洪县事业单位【完整版】《公共基础知识》新版必过复习资料/新版《公共基础知识》高分重点讲义/2.公共基础知识—专项特训/基础强化-哲学1.md",
    "02-知识点库/公共基础知识/泗洪县事业单位【完整版】《公共基础知识》新版必过复习资料/新版《公共基础知识》高分重点讲义/2.公共基础知识—专项特训/基础强化-民法2.md",
    "02-知识点库/公共基础知识/泗洪县事业单位【完整版】《公共基础知识》新版必过复习资料/新版《公共基础知识》高分重点讲义/2.公共基础知识—专项特训/基础强化-党史.md",
    "02-知识点库/公共基础知识/泗洪县事业单位【完整版】《公共基础知识》新版必过复习资料/新版《公共基础知识》高分重点讲义/2.公共基础知识—专项特训/基础强化-哲学3.md",
    "02-知识点库/公共基础知识/泗洪县事业单位【完整版】《公共基础知识》新版必过复习资料/新版《公共基础知识》高分重点讲义/2.公共基础知识—专项特训/基础强化-哲学2.md",
    "02-知识点库/公共基础知识/泗洪县事业单位【完整版】《公共基础知识》新版必过复习资料/新版《公共基础知识》高分重点讲义/2.公共基础知识—专项特训/基础强化-科技.md",
    "02-知识点库/公共基础知识/泗洪县事业单位【完整版】《公共基础知识》新版必过复习资料/新版《公共基础知识》高分重点讲义/2.公共基础知识—专项特训/基础强化-民法1.md",
    "02-知识点库/公共基础知识/最新泗洪县事业单位《公共基础知识》/九、核心精心整理资料——金牌讲义/九、核心独家资料——金牌讲义/公共基础知识讲义.pdf",
    "02-知识点库/公共基础知识/泗洪县事业单位【全新冲刺版】【公共基础知识】考点+预测押题库+重点必考+速学讲义/全新必过公共基础知识彩色笔记（答案）.pdf",
    "02-知识点库/公共基础知识/泗洪县事业单位【全新冲刺版】【公共基础知识】考点+预测押题库+重点必考+速学讲义/更新版【公共基础知识】高分笔记整合版知识点全覆盖.pdf",
    "02-知识点库/公共基础知识/泗洪县事业单位【全新冲刺版】【公共基础知识】考点+预测押题库+重点必考+速学讲义/全新公共基础知识预测押题题库/全新公共基础知识预测押题题库【答案解析】.pdf",
    "02-知识点库/公共基础知识/泗洪县事业单位【全新冲刺版】【公共基础知识】考点+预测押题库+重点必考+速学讲义/全新公共基础知识预测押题题库/全新公共基础知识预测押题题库.pdf",
    "01-真题库/历年真题/泗洪县事业单位综合知识与能力测试历年试题回忆版/2024年泗洪县事业单位真题和答案讲解/2024年宿迁泗洪县事业单位真题和答案.pdf",
    "01-真题库/历年真题/泗洪县事业单位综合知识与能力测试历年试题回忆版/2022泗洪事业单位真题及答案解析.pdf",
    "01-真题库/历年真题/泗洪县事业单位综合知识与能力测试历年试题回忆版/2019年江苏省事业单位招聘考试《综合知识与能力素质》真题及答案.pdf",
    "01-真题库/历年真题/泗洪县事业单位综合知识与能力测试历年试题回忆版/【真题整理】2020年泗洪县事业单位招聘真题复习及答案综合福_PDF密码解除.pdf",
    "02-知识点库/职业能力倾向测验/泗洪县事业单位【冲刺版重点必过】行政职业能力测试金牌讲义专项/【行测】必做100题/新版【行测】必做题库答案解析.pdf"
  ]
}